<pageBuilder>
	<request class='Page' method='setUri' />
	<request class='Page' method='setPointer' />
	<request class='Page' method='appendUriParams' />
	<request class='Page' method='loadData' />
	<request class='Page' method='loadContent' />
	<request class='Page' method='loadContentTemplate' />
	<request class='Page' method='loadMetaData' />
	<request class='Page' method='loadProperties' />
	<request class='Page' method='loadAttachments' />
	<request class='Page' method='loadRelatedPages' />
	<request class='Page' method='setTitle' />
	<request class='design' method='loadContentTemplate' />
	<request class='design' method='loadDesign' />
	<request class='design' method='setStyles' />
	<request class='design' method='setScripts' />
	<request class='design' method='setLayout' />
	<request class='Page' method='getPage' />
</pageBuilder>